vysp/__init__.py
vysp/client.py
vysp/exceptions.py
vysp_python-0.2.5.dist-info/METADATA
vysp_python-0.2.5.dist-info/WHEEL
vysp_python-0.2.5.dist-info/licenses/LICENSE
vysp_python-0.2.5.dist-info/RECORD
