Metadata-Version: 2.3
Name: vysp-python
Version: 0.2.5
Summary: Python Client Library for VYSP.AI
Project-URL: Homepage, https://vysp.ai
Project-URL: Documentation, https://docs.vysp.ai
Project-URL: Issues, https://vysp.ai/support
Author-email: VSY Design LLC <vijeet@vsy.one>
License-File: LICENSE
Classifier: License :: OSI Approved :: MIT License
Classifier: Operating System :: OS Independent
Classifier: Programming Language :: Python :: 3
Requires-Python: >=3.8
Requires-Dist: requests
